dbkit.py
dbkit-0.2.4.dist-info/METADATA
dbkit-0.2.4.dist-info/top_level.txt
dbkit-0.2.4.dist-info/metadata.json
dbkit-0.2.4.dist-info/DESCRIPTION.rst
dbkit-0.2.4.dist-info/WHEEL
dbkit-0.2.4.dist-info/RECORD
